tree_router/__init__.py
tree_router/router.py
tree_router/typing.py
tree_router/views.py
drf_tree_router-0.2.3.dist-info/LICENSE
drf_tree_router-0.2.3.dist-info/METADATA
drf_tree_router-0.2.3.dist-info/WHEEL
drf_tree_router-0.2.3.dist-info/RECORD
