Metadata-Version: 2.3
Name: drf-tree-router
Version: 0.2.3
Summary: Create browsable routes by nesting routers in a tree-like structure.
Home-page: https://mrthearman.github.io/drf-tree-router
License: MIT
Keywords: django,djangorestframework,drf,router,tree
Author: Matti Lamppu
Author-email: lamppu.matti.akseli@gmail.com
Requires-Python: >=3.10,<4
Classifier: Environment :: Web Environment
Classifier: Intended Audience :: Developers
Classifier: Operating System :: OS Independent
Classifier: Natural Language :: English
Classifier: Programming Language :: Python
Classifier: Programming Language :: Python :: 3
Classifier: Programming Language :: Python :: 3 :: Only
Classifier: Programming Language :: Python :: 3.10
Classifier: Programming Language :: Python :: 3.11
Classifier: Programming Language :: Python :: 3.12
Classifier: Programming Language :: Python :: 3.13
Classifier: Framework :: Django
Classifier: Framework :: Django :: 4.2
Classifier: Framework :: Django :: 5.0
Classifier: Framework :: Django :: 5.1
Requires-Dist: Django (>=4.2)
Requires-Dist: djangorestframework (>=3.14.0)
Project-URL: Bug Tracker, https://github.com/MrThearMan/drf-tree-router/issues
Project-URL: Documentation, https://mrthearman.github.io/drf-tree-router
Project-URL: Repository, https://github.com/MrThearMan/drf-tree-router
